MANIFEST.in
README.rst
requirements-test.txt
requirements.txt
setup.cfg
setup.py
sacrud_deform/__init__.py
sacrud_deform/common.py
sacrud_deform/widgets.py
sacrud_deform.egg-info/PKG-INFO
sacrud_deform.egg-info/SOURCES.txt
sacrud_deform.egg-info/dependency_links.txt
sacrud_deform.egg-info/not-zip-safe
sacrud_deform.egg-info/pbr.json
sacrud_deform.egg-info/requires.txt
sacrud_deform.egg-info/top_level.txt
sacrud_deform/templates/deform/Elfinder.pt
sacrud_deform/templates/deform/HiddenCheckbox.pt
sacrud_deform/templates/deform/Hstore.pt
sacrud_deform/templates/deform/Many2Many.pt
sacrud_deform/templates/deform/Slug.pt