Metadata-Version: 1.1
Name: sacrud-deform
Version: 0.1.4
Summary: Form generator for SQLAlchemy models.
Home-page: http://github.com/sacrud/sacrud_deform/
Author: Svintsov Dmitry
Author-email: root@uralbash.ru
License: MIT
Platform: UNKNOWN
Classifier: Development Status :: 5 - Production/Stable
Classifier: Environment :: Console
Classifier: Environment :: Web Environment
Classifier: Intended Audience :: Developers
Classifier: License :: OSI Approved :: MIT License
Classifier: Operating System :: OS Independent
Classifier: Programming Language :: Python
Classifier: Programming Language :: Python :: 2.6
Classifier: Programming Language :: Python :: 2.7
Classifier: Programming Language :: Python :: 3
Classifier: Programming Language :: Python :: 3.2
Classifier: Programming Language :: Python :: 3.3
Classifier: Programming Language :: Python :: 3.4
Classifier: Programming Language :: Python :: 3.5
Classifier: Framework :: Pyramid 
Classifier: Topic :: Internet
Classifier: Topic :: Database
